{"weekdays":[{"id":"03703_01001_4922","d":"1","st":[{"s":"bus_707220","t":"06:17"},{"s":"bus_018200","t":"06:19"},{"s":"bus_044400","t":"06:21"},{"s":"bus_043400","t":"06:22"},{"s":"bus_042400","t":"06:23"},{"s":"bus_021400","t":"06:24"},{"s":"bus_040420","t":"06:25"},{"s":"bus_548200","t":"06:26"},{"s":"bus_549200","t":"06:27"},{"s":"bus_550400","t":"06:28"},{"s":"bus_547400","t":"06:29"},{"s":"bus_036400","t":"06:30"},{"s":"bus_035400","t":"06:31"},{"s":"bus_034120","t":"06:32"},{"s":"bus_540400","t":"06:34"},{"s":"bus_541400","t":"06:35"},{"s":"bus_542100","t":"06:36"},{"s":"bus_543400","t":"06:37"},{"s":"bus_566400","t":"06:38"},{"s":"bus_567300","t":"06:40"},{"s":"bus_568300","t":"06:41"},{"s":"bus_569300","t":"06:42"},{"s":"bus_541300","t":"06:44"},{"s":"bus_540300","t":"06:45"},{"s":"bus_034220","t":"06:47"},{"s":"bus_035300","t":"06:48"},{"s":"bus_036300","t":"06:49"},{"s":"bus_547300","t":"06:50"},{"s":"bus_550100","t":"06:52"},{"s":"bus_549100","t":"06:53"},{"s":"bus_548100","t":"06:54"},{"s":"bus_040300","t":"06:56"},{"s":"bus_021300","t":"06:58"},{"s":"bus_042300","t":"06:59"},{"s":"bus_043300","t":"07:00"},{"s":"bus_044320","t":"07:01"},{"s":"bus_018100","t":"07:02"},{"s":"bus_707001","t":"07:05"}]},{"id":"03703_01001_5008","d":"1","st":[{"s":"bus_707220","t":"07:08"},{"s":"bus_018200","t":"07:10"},{"s":"bus_044400","t":"07:12"},{"s":"bus_043400","t":"07:13"},{"s":"bus_042400","t":"07:14"},{"s":"bus_021400","t":"07:15"},{"s":"bus_040420","t":"07:16"},{"s":"bus_548200","t":"07:17"},{"s":"bus_549200","t":"07:18"},{"s":"bus_550400","t":"07:19"},{"s":"bus_547400","t":"07:20"},{"s":"bus_036400","t":"07:21"},{"s":"bus_035400","t":"07:22"},{"s":"bus_034120","t":"07:23"},{"s":"bus_540400","t":"07:25"},{"s":"bus_541400","t":"07:26"},{"s":"bus_542100","t":"07:27"},{"s":"bus_543400","t":"07:28"},{"s":"bus_566400","t":"07:29"},{"s":"bus_567300","t":"07:31"},{"s":"bus_568300","t":"07:32"},{"s":"bus_569300","t":"07:33"},{"s":"bus_541300","t":"07:35"},{"s":"bus_540300","t":"07:36"},{"s":"bus_034220","t":"07:38"},{"s":"bus_035300","t":"07:39"},{"s":"bus_036300","t":"07:40"},{"s":"bus_547300","t":"07:41"},{"s":"bus_550100","t":"07:43"},{"s":"bus_549100","t":"07:44"},{"s":"bus_548100","t":"07:45"},{"s":"bus_040300","t":"07:47"},{"s":"bus_021300","t":"07:49"},{"s":"bus_042300","t":"07:50"},{"s":"bus_043300","t":"07:51"},{"s":"bus_044320","t":"07:53"},{"s":"bus_018100","t":"07:54"},{"s":"bus_707001","t":"07:57"}]},{"id":"03703_01001_5023","d":"1","st":[{"s":"bus_707220","t":"08:12"},{"s":"bus_018200","t":"08:14"},{"s":"bus_044400","t":"08:16"},{"s":"bus_043400","t":"08:17"},{"s":"bus_042400","t":"08:18"},{"s":"bus_021400","t":"08:20"},{"s":"bus_040420","t":"08:21"},{"s":"bus_548200","t":"08:22"},{"s":"bus_549200","t":"08:23"},{"s":"bus_550400","t":"08:24"},{"s":"bus_547400","t":"08:25"},{"s":"bus_036400","t":"08:26"},{"s":"bus_035400","t":"08:27"},{"s":"bus_034120","t":"08:29"},{"s":"bus_540400","t":"08:31"},{"s":"bus_541400","t":"08:32"},{"s":"bus_542100","t":"08:33"},{"s":"bus_543400","t":"08:34"},{"s":"bus_566400","t":"08:35"},{"s":"bus_567300","t":"08:37"},{"s":"bus_568300","t":"08:38"},{"s":"bus_569300","t":"08:39"},{"s":"bus_541300","t":"08:41"},{"s":"bus_540300","t":"08:42"},{"s":"bus_034220","t":"08:44"},{"s":"bus_035300","t":"08:45"},{"s":"bus_036300","t":"08:46"},{"s":"bus_547300","t":"08:47"},{"s":"bus_550100","t":"08:49"},{"s":"bus_549100","t":"08:50"},{"s":"bus_548100","t":"08:51"},{"s":"bus_040300","t":"08:53"},{"s":"bus_021300","t":"08:55"},{"s":"bus_042300","t":"08:56"},{"s":"bus_043300","t":"08:57"},{"s":"bus_044320","t":"08:59"},{"s":"bus_018100","t":"09:00"},{"s":"bus_707001","t":"09:03"}]},{"id":"03703_01001_4974","d":"1","st":[{"s":"bus_707220","t":"09:11"},{"s":"bus_018200","t":"09:13"},{"s":"bus_044400","t":"09:15"},{"s":"bus_043400","t":"09:16"},{"s":"bus_042400","t":"09:17"},{"s":"bus_021400","t":"09:19"},{"s":"bus_040420","t":"09:20"},{"s":"bus_548200","t":"09:21"},{"s":"bus_549200","t":"09:22"},{"s":"bus_550400","t":"09:23"},{"s":"bus_547400","t":"09:24"},{"s":"bus_036400","t":"09:25"},{"s":"bus_035400","t":"09:26"},{"s":"bus_034120","t":"09:28"},{"s":"bus_540400","t":"09:30"},{"s":"bus_541400","t":"09:31"},{"s":"bus_542100","t":"09:32"},{"s":"bus_543400","t":"09:33"},{"s":"bus_566400","t":"09:34"},{"s":"bus_567300","t":"09:36"},{"s":"bus_568300","t":"09:37"},{"s":"bus_569300","t":"09:38"},{"s":"bus_541300","t":"09:40"},{"s":"bus_540300","t":"09:41"},{"s":"bus_034220","t":"09:43"},{"s":"bus_035300","t":"09:44"},{"s":"bus_036300","t":"09:45"},{"s":"bus_547300","t":"09:46"},{"s":"bus_550100","t":"09:48"},{"s":"bus_549100","t":"09:49"},{"s":"bus_548100","t":"09:50"},{"s":"bus_040300","t":"09:52"},{"s":"bus_021300","t":"09:54"},{"s":"bus_042300","t":"09:55"},{"s":"bus_043300","t":"09:56"},{"s":"bus_044320","t":"09:58"},{"s":"bus_018100","t":"09:59"},{"s":"bus_707001","t":"10:02"}]},{"id":"03703_01001_5045","d":"1","st":[{"s":"bus_707220","t":"10:11"},{"s":"bus_018200","t":"10:13"},{"s":"bus_044400","t":"10:15"},{"s":"bus_043400","t":"10:16"},{"s":"bus_042400","t":"10:17"},{"s":"bus_021400","t":"10:19"},{"s":"bus_040420","t":"10:20"},{"s":"bus_548200","t":"10:21"},{"s":"bus_549200","t":"10:22"},{"s":"bus_550400","t":"10:23"},{"s":"bus_547400","t":"10:24"},{"s":"bus_036400","t":"10:25"},{"s":"bus_035400","t":"10:26"},{"s":"bus_034120","t":"10:28"},{"s":"bus_540400","t":"10:30"},{"s":"bus_541400","t":"10:31"},{"s":"bus_542100","t":"10:32"},{"s":"bus_543400","t":"10:33"},{"s":"bus_566400","t":"10:34"},{"s":"bus_567300","t":"10:36"},{"s":"bus_568300","t":"10:37"},{"s":"bus_569300","t":"10:38"},{"s":"bus_541300","t":"10:40"},{"s":"bus_540300","t":"10:41"},{"s":"bus_034220","t":"10:43"},{"s":"bus_035300","t":"10:44"},{"s":"bus_036300","t":"10:45"},{"s":"bus_547300","t":"10:46"},{"s":"bus_550100","t":"10:48"},{"s":"bus_549100","t":"10:49"},{"s":"bus_548100","t":"10:50"},{"s":"bus_040300","t":"10:52"},{"s":"bus_021300","t":"10:54"},{"s":"bus_042300","t":"10:55"},{"s":"bus_043300","t":"10:56"},{"s":"bus_044320","t":"10:58"},{"s":"bus_018100","t":"10:59"},{"s":"bus_707001","t":"11:02"}]},{"id":"03703_01001_5065","d":"1","st":[{"s":"bus_707220","t":"11:41"},{"s":"bus_018200","t":"11:43"},{"s":"bus_044400","t":"11:45"},{"s":"bus_043400","t":"11:46"},{"s":"bus_042400","t":"11:47"},{"s":"bus_021400","t":"11:49"},{"s":"bus_040420","t":"11:50"},{"s":"bus_548200","t":"11:51"},{"s":"bus_549200","t":"11:52"},{"s":"bus_550400","t":"11:53"},{"s":"bus_547400","t":"11:54"},{"s":"bus_036400","t":"11:55"},{"s":"bus_035400","t":"11:56"},{"s":"bus_034120","t":"11:58"},{"s":"bus_540400","t":"12:00"},{"s":"bus_541400","t":"12:01"},{"s":"bus_542100","t":"12:02"},{"s":"bus_543400","t":"12:03"},{"s":"bus_566400","t":"12:04"},{"s":"bus_567300","t":"12:06"},{"s":"bus_568300","t":"12:07"},{"s":"bus_569300","t":"12:08"},{"s":"bus_541300","t":"12:10"},{"s":"bus_540300","t":"12:11"},{"s":"bus_034220","t":"12:13"},{"s":"bus_035300","t":"12:14"},{"s":"bus_036300","t":"12:15"},{"s":"bus_547300","t":"12:16"},{"s":"bus_550100","t":"12:18"},{"s":"bus_549100","t":"12:19"},{"s":"bus_548100","t":"12:20"},{"s":"bus_040300","t":"12:22"},{"s":"bus_021300","t":"12:24"},{"s":"bus_042300","t":"12:25"},{"s":"bus_043300","t":"12:26"},{"s":"bus_044320","t":"12:28"},{"s":"bus_018100","t":"12:29"},{"s":"bus_707001","t":"12:32"}]},{"id":"03703_01001_5066","d":"1","st":[{"s":"bus_707220","t":"13:11"},{"s":"bus_018200","t":"13:13"},{"s":"bus_044400","t":"13:15"},{"s":"bus_043400","t":"13:16"},{"s":"bus_042400","t":"13:17"},{"s":"bus_021400","t":"13:19"},{"s":"bus_040420","t":"13:20"},{"s":"bus_548200","t":"13:21"},{"s":"bus_549200","t":"13:22"},{"s":"bus_550400","t":"13:23"},{"s":"bus_547400","t":"13:24"},{"s":"bus_036400","t":"13:25"},{"s":"bus_035400","t":"13:26"},{"s":"bus_034120","t":"13:28"},{"s":"bus_540400","t":"13:30"},{"s":"bus_541400","t":"13:31"},{"s":"bus_542100","t":"13:32"},{"s":"bus_543400","t":"13:33"},{"s":"bus_566400","t":"13:34"},{"s":"bus_567300","t":"13:36"},{"s":"bus_568300","t":"13:37"},{"s":"bus_569300","t":"13:38"},{"s":"bus_541300","t":"13:40"},{"s":"bus_540300","t":"13:41"},{"s":"bus_034220","t":"13:43"},{"s":"bus_035300","t":"13:44"},{"s":"bus_036300","t":"13:45"},{"s":"bus_547300","t":"13:46"},{"s":"bus_550100","t":"13:48"},{"s":"bus_549100","t":"13:49"},{"s":"bus_548100","t":"13:50"},{"s":"bus_040300","t":"13:52"},{"s":"bus_021300","t":"13:54"},{"s":"bus_042300","t":"13:55"},{"s":"bus_043300","t":"13:56"},{"s":"bus_044320","t":"13:58"},{"s":"bus_018100","t":"13:59"},{"s":"bus_707001","t":"14:02"}]},{"id":"03703_01001_4932","d":"1","st":[{"s":"bus_707220","t":"14:41"},{"s":"bus_018200","t":"14:43"},{"s":"bus_044400","t":"14:45"},{"s":"bus_043400","t":"14:46"},{"s":"bus_042400","t":"14:47"},{"s":"bus_021400","t":"14:49"},{"s":"bus_040420","t":"14:50"},{"s":"bus_548200","t":"14:51"},{"s":"bus_549200","t":"14:52"},{"s":"bus_550400","t":"14:53"},{"s":"bus_547400","t":"14:54"},{"s":"bus_036400","t":"14:55"},{"s":"bus_035400","t":"14:56"},{"s":"bus_034120","t":"14:58"},{"s":"bus_540400","t":"15:00"},{"s":"bus_541400","t":"15:01"},{"s":"bus_542100","t":"15:02"},{"s":"bus_543400","t":"15:03"},{"s":"bus_566400","t":"15:04"},{"s":"bus_567300","t":"15:06"},{"s":"bus_568300","t":"15:07"},{"s":"bus_569300","t":"15:08"},{"s":"bus_541300","t":"15:10"},{"s":"bus_540300","t":"15:11"},{"s":"bus_034220","t":"15:13"},{"s":"bus_035300","t":"15:14"},{"s":"bus_036300","t":"15:15"},{"s":"bus_547300","t":"15:16"},{"s":"bus_550100","t":"15:18"},{"s":"bus_549100","t":"15:19"},{"s":"bus_548100","t":"15:20"},{"s":"bus_040300","t":"15:22"},{"s":"bus_021300","t":"15:24"},{"s":"bus_042300","t":"15:25"},{"s":"bus_043300","t":"15:26"},{"s":"bus_044320","t":"15:28"},{"s":"bus_018100","t":"15:29"},{"s":"bus_707001","t":"15:32"}]},{"id":"03703_01001_5078","d":"1","st":[{"s":"bus_707220","t":"16:11"},{"s":"bus_018200","t":"16:13"},{"s":"bus_044400","t":"16:15"},{"s":"bus_043400","t":"16:16"},{"s":"bus_042400","t":"16:17"},{"s":"bus_021400","t":"16:19"},{"s":"bus_040420","t":"16:20"},{"s":"bus_548200","t":"16:21"},{"s":"bus_549200","t":"16:22"},{"s":"bus_550400","t":"16:23"},{"s":"bus_547400","t":"16:24"},{"s":"bus_036400","t":"16:25"},{"s":"bus_035400","t":"16:26"},{"s":"bus_034120","t":"16:28"},{"s":"bus_540400","t":"16:30"},{"s":"bus_541400","t":"16:31"},{"s":"bus_542100","t":"16:32"},{"s":"bus_543400","t":"16:33"},{"s":"bus_566400","t":"16:34"},{"s":"bus_567300","t":"16:36"},{"s":"bus_568300","t":"16:37"},{"s":"bus_569300","t":"16:38"},{"s":"bus_541300","t":"16:40"},{"s":"bus_540300","t":"16:41"},{"s":"bus_034220","t":"16:43"},{"s":"bus_035300","t":"16:44"},{"s":"bus_036300","t":"16:45"},{"s":"bus_547300","t":"16:46"},{"s":"bus_550100","t":"16:48"},{"s":"bus_549100","t":"16:49"},{"s":"bus_548100","t":"16:50"},{"s":"bus_040300","t":"16:52"},{"s":"bus_021300","t":"16:54"},{"s":"bus_042300","t":"16:55"},{"s":"bus_043300","t":"16:56"},{"s":"bus_044320","t":"16:58"},{"s":"bus_018100","t":"16:59"},{"s":"bus_707001","t":"17:02"}]},{"id":"03703_01001_5037","d":"1","st":[{"s":"bus_707220","t":"17:11"},{"s":"bus_018200","t":"17:13"},{"s":"bus_044400","t":"17:15"},{"s":"bus_043400","t":"17:16"},{"s":"bus_042400","t":"17:17"},{"s":"bus_021400","t":"17:19"},{"s":"bus_040420","t":"17:20"},{"s":"bus_548200","t":"17:21"},{"s":"bus_549200","t":"17:22"},{"s":"bus_550400","t":"17:23"},{"s":"bus_547400","t":"17:24"},{"s":"bus_036400","t":"17:25"},{"s":"bus_035400","t":"17:26"},{"s":"bus_034120","t":"17:28"},{"s":"bus_540400","t":"17:30"},{"s":"bus_541400","t":"17:31"},{"s":"bus_542100","t":"17:32"},{"s":"bus_543400","t":"17:33"},{"s":"bus_566400","t":"17:34"},{"s":"bus_567300","t":"17:36"},{"s":"bus_568300","t":"17:37"},{"s":"bus_569300","t":"17:38"},{"s":"bus_541300","t":"17:40"},{"s":"bus_540300","t":"17:41"},{"s":"bus_034220","t":"17:43"},{"s":"bus_035300","t":"17:44"},{"s":"bus_036300","t":"17:45"},{"s":"bus_547300","t":"17:46"},{"s":"bus_550100","t":"17:48"},{"s":"bus_549100","t":"17:49"},{"s":"bus_548100","t":"17:50"},{"s":"bus_040300","t":"17:52"},{"s":"bus_021300","t":"17:54"},{"s":"bus_042300","t":"17:55"},{"s":"bus_043300","t":"17:56"},{"s":"bus_044320","t":"17:58"},{"s":"bus_018100","t":"17:59"},{"s":"bus_707001","t":"18:02"}]},{"id":"03703_01001_5079","d":"1","st":[{"s":"bus_707220","t":"18:11"},{"s":"bus_018200","t":"18:13"},{"s":"bus_044400","t":"18:15"},{"s":"bus_043400","t":"18:16"},{"s":"bus_042400","t":"18:17"},{"s":"bus_021400","t":"18:19"},{"s":"bus_040420","t":"18:20"},{"s":"bus_548200","t":"18:21"},{"s":"bus_549200","t":"18:22"},{"s":"bus_550400","t":"18:23"},{"s":"bus_547400","t":"18:24"},{"s":"bus_036400","t":"18:25"},{"s":"bus_035400","t":"18:26"},{"s":"bus_034120","t":"18:28"},{"s":"bus_540400","t":"18:30"},{"s":"bus_541400","t":"18:31"},{"s":"bus_542100","t":"18:32"},{"s":"bus_543400","t":"18:33"},{"s":"bus_566400","t":"18:34"},{"s":"bus_567300","t":"18:36"},{"s":"bus_568300","t":"18:37"},{"s":"bus_569300","t":"18:38"},{"s":"bus_541300","t":"18:40"},{"s":"bus_540300","t":"18:41"},{"s":"bus_034220","t":"18:43"},{"s":"bus_035300","t":"18:44"},{"s":"bus_036300","t":"18:45"},{"s":"bus_547300","t":"18:46"},{"s":"bus_550100","t":"18:48"},{"s":"bus_549100","t":"18:49"},{"s":"bus_548100","t":"18:50"},{"s":"bus_040300","t":"18:52"},{"s":"bus_021300","t":"18:54"},{"s":"bus_042300","t":"18:55"},{"s":"bus_043300","t":"18:56"},{"s":"bus_044320","t":"18:58"},{"s":"bus_018100","t":"18:59"},{"s":"bus_707001","t":"19:02"}]},{"id":"03703_01001_5080","d":"1","st":[{"s":"bus_707220","t":"19:35"},{"s":"bus_018200","t":"19:37"},{"s":"bus_044400","t":"19:39"},{"s":"bus_043400","t":"19:40"},{"s":"bus_042400","t":"19:41"},{"s":"bus_021400","t":"19:42"},{"s":"bus_040420","t":"19:43"},{"s":"bus_548200","t":"19:44"},{"s":"bus_549200","t":"19:45"},{"s":"bus_550400","t":"19:46"},{"s":"bus_547400","t":"19:47"},{"s":"bus_036400","t":"19:48"},{"s":"bus_035400","t":"19:49"},{"s":"bus_034120","t":"19:51"},{"s":"bus_540400","t":"19:53"},{"s":"bus_541400","t":"19:54"},{"s":"bus_542100","t":"19:55"},{"s":"bus_543400","t":"19:56"},{"s":"bus_566400","t":"19:57"},{"s":"bus_567300","t":"19:59"},{"s":"bus_568300","t":"20:00"},{"s":"bus_569300","t":"20:01"},{"s":"bus_541300","t":"20:03"},{"s":"bus_540300","t":"20:04"},{"s":"bus_034220","t":"20:06"},{"s":"bus_035300","t":"20:07"},{"s":"bus_036300","t":"20:08"},{"s":"bus_547300","t":"20:09"},{"s":"bus_550100","t":"20:11"},{"s":"bus_549100","t":"20:12"},{"s":"bus_548100","t":"20:13"},{"s":"bus_040300","t":"20:15"},{"s":"bus_021300","t":"20:17"},{"s":"bus_042300","t":"20:18"},{"s":"bus_043300","t":"20:19"},{"s":"bus_044320","t":"20:20"},{"s":"bus_018100","t":"20:21"},{"s":"bus_707001","t":"20:24"}]},{"id":"03703_01001_5072","d":"1","st":[{"s":"bus_707220","t":"21:06"},{"s":"bus_018200","t":"21:08"},{"s":"bus_044400","t":"21:10"},{"s":"bus_043400","t":"21:11"},{"s":"bus_042400","t":"21:12"},{"s":"bus_021400","t":"21:13"},{"s":"bus_040420","t":"21:14"},{"s":"bus_548200","t":"21:15"},{"s":"bus_549200","t":"21:16"},{"s":"bus_550400","t":"21:17"},{"s":"bus_547400","t":"21:18"},{"s":"bus_036400","t":"21:19"},{"s":"bus_035400","t":"21:20"},{"s":"bus_034120","t":"21:22"},{"s":"bus_540400","t":"21:24"},{"s":"bus_541400","t":"21:25"},{"s":"bus_542100","t":"21:26"},{"s":"bus_543400","t":"21:27"},{"s":"bus_566400","t":"21:28"},{"s":"bus_567300","t":"21:30"},{"s":"bus_568300","t":"21:31"},{"s":"bus_569300","t":"21:32"},{"s":"bus_541300","t":"21:34"},{"s":"bus_540300","t":"21:35"},{"s":"bus_034220","t":"21:37"},{"s":"bus_035300","t":"21:38"},{"s":"bus_036300","t":"21:39"},{"s":"bus_547300","t":"21:40"},{"s":"bus_550100","t":"21:42"},{"s":"bus_549100","t":"21:43"},{"s":"bus_548100","t":"21:44"},{"s":"bus_040300","t":"21:46"},{"s":"bus_021300","t":"21:48"},{"s":"bus_042300","t":"21:49"},{"s":"bus_043300","t":"21:50"},{"s":"bus_044320","t":"21:51"},{"s":"bus_018100","t":"21:52"},{"s":"bus_707001","t":"21:55"}]}],"saturdays":[{"id":"03703_03001_10438","d":"1","st":[{"s":"bus_707220","t":"06:17"},{"s":"bus_018200","t":"06:19"},{"s":"bus_044400","t":"06:21"},{"s":"bus_043400","t":"06:22"},{"s":"bus_042400","t":"06:23"},{"s":"bus_021400","t":"06:24"},{"s":"bus_040420","t":"06:25"},{"s":"bus_548200","t":"06:26"},{"s":"bus_549200","t":"06:27"},{"s":"bus_550400","t":"06:28"},{"s":"bus_547400","t":"06:29"},{"s":"bus_036400","t":"06:30"},{"s":"bus_035400","t":"06:31"},{"s":"bus_034120","t":"06:32"},{"s":"bus_540400","t":"06:34"},{"s":"bus_541400","t":"06:35"},{"s":"bus_542100","t":"06:36"},{"s":"bus_543400","t":"06:37"},{"s":"bus_566400","t":"06:38"},{"s":"bus_567300","t":"06:40"},{"s":"bus_568300","t":"06:41"},{"s":"bus_569300","t":"06:42"},{"s":"bus_541300","t":"06:44"},{"s":"bus_540300","t":"06:45"},{"s":"bus_034220","t":"06:47"},{"s":"bus_035300","t":"06:48"},{"s":"bus_036300","t":"06:49"},{"s":"bus_547300","t":"06:50"},{"s":"bus_550100","t":"06:52"},{"s":"bus_549100","t":"06:53"},{"s":"bus_548100","t":"06:54"},{"s":"bus_040300","t":"06:56"},{"s":"bus_021300","t":"06:58"},{"s":"bus_042300","t":"06:59"},{"s":"bus_043300","t":"07:00"},{"s":"bus_044320","t":"07:01"},{"s":"bus_018100","t":"07:02"},{"s":"bus_707001","t":"07:05"}]},{"id":"03703_03001_10471","d":"1","st":[{"s":"bus_707220","t":"07:08"},{"s":"bus_018200","t":"07:10"},{"s":"bus_044400","t":"07:12"},{"s":"bus_043400","t":"07:13"},{"s":"bus_042400","t":"07:14"},{"s":"bus_021400","t":"07:15"},{"s":"bus_040420","t":"07:16"},{"s":"bus_548200","t":"07:17"},{"s":"bus_549200","t":"07:18"},{"s":"bus_550400","t":"07:19"},{"s":"bus_547400","t":"07:20"},{"s":"bus_036400","t":"07:21"},{"s":"bus_035400","t":"07:22"},{"s":"bus_034120","t":"07:23"},{"s":"bus_540400","t":"07:25"},{"s":"bus_541400","t":"07:26"},{"s":"bus_542100","t":"07:27"},{"s":"bus_543400","t":"07:28"},{"s":"bus_566400","t":"07:29"},{"s":"bus_567300","t":"07:31"},{"s":"bus_568300","t":"07:32"},{"s":"bus_569300","t":"07:33"},{"s":"bus_541300","t":"07:35"},{"s":"bus_540300","t":"07:36"},{"s":"bus_034220","t":"07:38"},{"s":"bus_035300","t":"07:39"},{"s":"bus_036300","t":"07:40"},{"s":"bus_547300","t":"07:41"},{"s":"bus_550100","t":"07:43"},{"s":"bus_549100","t":"07:44"},{"s":"bus_548100","t":"07:45"},{"s":"bus_040300","t":"07:47"},{"s":"bus_021300","t":"07:49"},{"s":"bus_042300","t":"07:50"},{"s":"bus_043300","t":"07:51"},{"s":"bus_044320","t":"07:52"},{"s":"bus_018100","t":"07:53"},{"s":"bus_707001","t":"07:56"}]},{"id":"03703_03001_10481","d":"1","st":[{"s":"bus_707220","t":"08:14"},{"s":"bus_018200","t":"08:16"},{"s":"bus_044400","t":"08:18"},{"s":"bus_043400","t":"08:19"},{"s":"bus_042400","t":"08:20"},{"s":"bus_021400","t":"08:21"},{"s":"bus_040420","t":"08:22"},{"s":"bus_548200","t":"08:23"},{"s":"bus_549200","t":"08:24"},{"s":"bus_550400","t":"08:25"},{"s":"bus_547400","t":"08:26"},{"s":"bus_036400","t":"08:27"},{"s":"bus_035400","t":"08:28"},{"s":"bus_034120","t":"08:29"},{"s":"bus_540400","t":"08:31"},{"s":"bus_541400","t":"08:32"},{"s":"bus_542100","t":"08:33"},{"s":"bus_543400","t":"08:34"},{"s":"bus_566400","t":"08:35"},{"s":"bus_567300","t":"08:37"},{"s":"bus_568300","t":"08:38"},{"s":"bus_569300","t":"08:39"},{"s":"bus_541300","t":"08:41"},{"s":"bus_540300","t":"08:42"},{"s":"bus_034220","t":"08:44"},{"s":"bus_035300","t":"08:45"},{"s":"bus_036300","t":"08:46"},{"s":"bus_547300","t":"08:47"},{"s":"bus_550100","t":"08:49"},{"s":"bus_549100","t":"08:50"},{"s":"bus_548100","t":"08:51"},{"s":"bus_040300","t":"08:53"},{"s":"bus_021300","t":"08:55"},{"s":"bus_042300","t":"08:56"},{"s":"bus_043300","t":"08:57"},{"s":"bus_044320","t":"08:59"},{"s":"bus_018100","t":"09:00"},{"s":"bus_707001","t":"09:03"}]},{"id":"03703_03001_10465","d":"1","st":[{"s":"bus_707220","t":"09:11"},{"s":"bus_018200","t":"09:13"},{"s":"bus_044400","t":"09:15"},{"s":"bus_043400","t":"09:16"},{"s":"bus_042400","t":"09:17"},{"s":"bus_021400","t":"09:19"},{"s":"bus_040420","t":"09:20"},{"s":"bus_548200","t":"09:21"},{"s":"bus_549200","t":"09:22"},{"s":"bus_550400","t":"09:23"},{"s":"bus_547400","t":"09:24"},{"s":"bus_036400","t":"09:25"},{"s":"bus_035400","t":"09:26"},{"s":"bus_034120","t":"09:28"},{"s":"bus_540400","t":"09:30"},{"s":"bus_541400","t":"09:31"},{"s":"bus_542100","t":"09:32"},{"s":"bus_543400","t":"09:33"},{"s":"bus_566400","t":"09:34"},{"s":"bus_567300","t":"09:36"},{"s":"bus_568300","t":"09:37"},{"s":"bus_569300","t":"09:38"},{"s":"bus_541300","t":"09:40"},{"s":"bus_540300","t":"09:41"},{"s":"bus_034220","t":"09:43"},{"s":"bus_035300","t":"09:44"},{"s":"bus_036300","t":"09:45"},{"s":"bus_547300","t":"09:46"},{"s":"bus_550100","t":"09:48"},{"s":"bus_549100","t":"09:49"},{"s":"bus_548100","t":"09:50"},{"s":"bus_040300","t":"09:52"},{"s":"bus_021300","t":"09:54"},{"s":"bus_042300","t":"09:55"},{"s":"bus_043300","t":"09:56"},{"s":"bus_044320","t":"09:58"},{"s":"bus_018100","t":"09:59"},{"s":"bus_707001","t":"10:02"}]},{"id":"03703_03001_10445","d":"1","st":[{"s":"bus_707220","t":"10:11"},{"s":"bus_018200","t":"10:13"},{"s":"bus_044400","t":"10:15"},{"s":"bus_043400","t":"10:16"},{"s":"bus_042400","t":"10:17"},{"s":"bus_021400","t":"10:19"},{"s":"bus_040420","t":"10:20"},{"s":"bus_548200","t":"10:21"},{"s":"bus_549200","t":"10:22"},{"s":"bus_550400","t":"10:23"},{"s":"bus_547400","t":"10:24"},{"s":"bus_036400","t":"10:25"},{"s":"bus_035400","t":"10:26"},{"s":"bus_034120","t":"10:28"},{"s":"bus_540400","t":"10:30"},{"s":"bus_541400","t":"10:31"},{"s":"bus_542100","t":"10:32"},{"s":"bus_543400","t":"10:33"},{"s":"bus_566400","t":"10:34"},{"s":"bus_567300","t":"10:36"},{"s":"bus_568300","t":"10:37"},{"s":"bus_569300","t":"10:38"},{"s":"bus_541300","t":"10:40"},{"s":"bus_540300","t":"10:41"},{"s":"bus_034220","t":"10:43"},{"s":"bus_035300","t":"10:44"},{"s":"bus_036300","t":"10:45"},{"s":"bus_547300","t":"10:46"},{"s":"bus_550100","t":"10:48"},{"s":"bus_549100","t":"10:49"},{"s":"bus_548100","t":"10:50"},{"s":"bus_040300","t":"10:52"},{"s":"bus_021300","t":"10:54"},{"s":"bus_042300","t":"10:55"},{"s":"bus_043300","t":"10:56"},{"s":"bus_044320","t":"10:58"},{"s":"bus_018100","t":"10:59"},{"s":"bus_707001","t":"11:02"}]},{"id":"03703_03001_10486","d":"1","st":[{"s":"bus_707220","t":"11:41"},{"s":"bus_018200","t":"11:43"},{"s":"bus_044400","t":"11:45"},{"s":"bus_043400","t":"11:46"},{"s":"bus_042400","t":"11:47"},{"s":"bus_021400","t":"11:49"},{"s":"bus_040420","t":"11:50"},{"s":"bus_548200","t":"11:51"},{"s":"bus_549200","t":"11:52"},{"s":"bus_550400","t":"11:53"},{"s":"bus_547400","t":"11:54"},{"s":"bus_036400","t":"11:55"},{"s":"bus_035400","t":"11:56"},{"s":"bus_034120","t":"11:58"},{"s":"bus_540400","t":"12:00"},{"s":"bus_541400","t":"12:01"},{"s":"bus_542100","t":"12:02"},{"s":"bus_543400","t":"12:03"},{"s":"bus_566400","t":"12:04"},{"s":"bus_567300","t":"12:06"},{"s":"bus_568300","t":"12:07"},{"s":"bus_569300","t":"12:08"},{"s":"bus_541300","t":"12:10"},{"s":"bus_540300","t":"12:11"},{"s":"bus_034220","t":"12:13"},{"s":"bus_035300","t":"12:14"},{"s":"bus_036300","t":"12:15"},{"s":"bus_547300","t":"12:16"},{"s":"bus_550100","t":"12:18"},{"s":"bus_549100","t":"12:19"},{"s":"bus_548100","t":"12:20"},{"s":"bus_040300","t":"12:22"},{"s":"bus_021300","t":"12:24"},{"s":"bus_042300","t":"12:25"},{"s":"bus_043300","t":"12:26"},{"s":"bus_044320","t":"12:28"},{"s":"bus_018100","t":"12:29"},{"s":"bus_707001","t":"12:32"}]},{"id":"03703_03001_10487","d":"1","st":[{"s":"bus_707220","t":"13:11"},{"s":"bus_018200","t":"13:13"},{"s":"bus_044400","t":"13:15"},{"s":"bus_043400","t":"13:16"},{"s":"bus_042400","t":"13:17"},{"s":"bus_021400","t":"13:19"},{"s":"bus_040420","t":"13:20"},{"s":"bus_548200","t":"13:21"},{"s":"bus_549200","t":"13:22"},{"s":"bus_550400","t":"13:23"},{"s":"bus_547400","t":"13:24"},{"s":"bus_036400","t":"13:25"},{"s":"bus_035400","t":"13:26"},{"s":"bus_034120","t":"13:28"},{"s":"bus_540400","t":"13:30"},{"s":"bus_541400","t":"13:31"},{"s":"bus_542100","t":"13:32"},{"s":"bus_543400","t":"13:33"},{"s":"bus_566400","t":"13:34"},{"s":"bus_567300","t":"13:36"},{"s":"bus_568300","t":"13:37"},{"s":"bus_569300","t":"13:38"},{"s":"bus_541300","t":"13:40"},{"s":"bus_540300","t":"13:41"},{"s":"bus_034220","t":"13:43"},{"s":"bus_035300","t":"13:44"},{"s":"bus_036300","t":"13:45"},{"s":"bus_547300","t":"13:46"},{"s":"bus_550100","t":"13:48"},{"s":"bus_549100","t":"13:49"},{"s":"bus_548100","t":"13:50"},{"s":"bus_040300","t":"13:52"},{"s":"bus_021300","t":"13:54"},{"s":"bus_042300","t":"13:55"},{"s":"bus_043300","t":"13:56"},{"s":"bus_044320","t":"13:58"},{"s":"bus_018100","t":"13:59"},{"s":"bus_707001","t":"14:02"}]},{"id":"03703_03001_10448","d":"1","st":[{"s":"bus_707220","t":"14:41"},{"s":"bus_018200","t":"14:43"},{"s":"bus_044400","t":"14:45"},{"s":"bus_043400","t":"14:46"},{"s":"bus_042400","t":"14:47"},{"s":"bus_021400","t":"14:49"},{"s":"bus_040420","t":"14:50"},{"s":"bus_548200","t":"14:51"},{"s":"bus_549200","t":"14:52"},{"s":"bus_550400","t":"14:53"},{"s":"bus_547400","t":"14:54"},{"s":"bus_036400","t":"14:55"},{"s":"bus_035400","t":"14:56"},{"s":"bus_034120","t":"14:58"},{"s":"bus_540400","t":"15:00"},{"s":"bus_541400","t":"15:01"},{"s":"bus_542100","t":"15:02"},{"s":"bus_543400","t":"15:03"},{"s":"bus_566400","t":"15:04"},{"s":"bus_567300","t":"15:06"},{"s":"bus_568300","t":"15:07"},{"s":"bus_569300","t":"15:08"},{"s":"bus_541300","t":"15:10"},{"s":"bus_540300","t":"15:11"},{"s":"bus_034220","t":"15:13"},{"s":"bus_035300","t":"15:14"},{"s":"bus_036300","t":"15:15"},{"s":"bus_547300","t":"15:16"},{"s":"bus_550100","t":"15:18"},{"s":"bus_549100","t":"15:19"},{"s":"bus_548100","t":"15:20"},{"s":"bus_040300","t":"15:22"},{"s":"bus_021300","t":"15:24"},{"s":"bus_042300","t":"15:25"},{"s":"bus_043300","t":"15:26"},{"s":"bus_044320","t":"15:28"},{"s":"bus_018100","t":"15:29"},{"s":"bus_707001","t":"15:32"}]},{"id":"03703_03001_10556","d":"1","st":[{"s":"bus_707220","t":"16:11"},{"s":"bus_018200","t":"16:13"},{"s":"bus_044400","t":"16:15"},{"s":"bus_043400","t":"16:16"},{"s":"bus_042400","t":"16:17"},{"s":"bus_021400","t":"16:19"},{"s":"bus_040420","t":"16:20"},{"s":"bus_548200","t":"16:21"},{"s":"bus_549200","t":"16:22"},{"s":"bus_550400","t":"16:23"},{"s":"bus_547400","t":"16:24"},{"s":"bus_036400","t":"16:25"},{"s":"bus_035400","t":"16:26"},{"s":"bus_034120","t":"16:28"},{"s":"bus_540400","t":"16:30"},{"s":"bus_541400","t":"16:31"},{"s":"bus_542100","t":"16:32"},{"s":"bus_543400","t":"16:33"},{"s":"bus_566400","t":"16:34"},{"s":"bus_567300","t":"16:36"},{"s":"bus_568300","t":"16:37"},{"s":"bus_569300","t":"16:38"},{"s":"bus_541300","t":"16:40"},{"s":"bus_540300","t":"16:41"},{"s":"bus_034220","t":"16:43"},{"s":"bus_035300","t":"16:44"},{"s":"bus_036300","t":"16:45"},{"s":"bus_547300","t":"16:46"},{"s":"bus_550100","t":"16:48"},{"s":"bus_549100","t":"16:49"},{"s":"bus_548100","t":"16:50"},{"s":"bus_040300","t":"16:52"},{"s":"bus_021300","t":"16:54"},{"s":"bus_042300","t":"16:55"},{"s":"bus_043300","t":"16:56"},{"s":"bus_044320","t":"16:58"},{"s":"bus_018100","t":"16:59"},{"s":"bus_707001","t":"17:02"}]},{"id":"03703_03001_10480","d":"1","st":[{"s":"bus_707220","t":"17:11"},{"s":"bus_018200","t":"17:13"},{"s":"bus_044400","t":"17:15"},{"s":"bus_043400","t":"17:16"},{"s":"bus_042400","t":"17:17"},{"s":"bus_021400","t":"17:19"},{"s":"bus_040420","t":"17:20"},{"s":"bus_548200","t":"17:21"},{"s":"bus_549200","t":"17:22"},{"s":"bus_550400","t":"17:23"},{"s":"bus_547400","t":"17:24"},{"s":"bus_036400","t":"17:25"},{"s":"bus_035400","t":"17:26"},{"s":"bus_034120","t":"17:28"},{"s":"bus_540400","t":"17:30"},{"s":"bus_541400","t":"17:31"},{"s":"bus_542100","t":"17:32"},{"s":"bus_543400","t":"17:33"},{"s":"bus_566400","t":"17:34"},{"s":"bus_567300","t":"17:36"},{"s":"bus_568300","t":"17:37"},{"s":"bus_569300","t":"17:38"},{"s":"bus_541300","t":"17:40"},{"s":"bus_540300","t":"17:41"},{"s":"bus_034220","t":"17:43"},{"s":"bus_035300","t":"17:44"},{"s":"bus_036300","t":"17:45"},{"s":"bus_547300","t":"17:46"},{"s":"bus_550100","t":"17:48"},{"s":"bus_549100","t":"17:49"},{"s":"bus_548100","t":"17:50"},{"s":"bus_040300","t":"17:52"},{"s":"bus_021300","t":"17:54"},{"s":"bus_042300","t":"17:55"},{"s":"bus_043300","t":"17:56"},{"s":"bus_044320","t":"17:58"},{"s":"bus_018100","t":"17:59"},{"s":"bus_707001","t":"18:02"}]},{"id":"03703_03001_10557","d":"1","st":[{"s":"bus_707220","t":"18:11"},{"s":"bus_018200","t":"18:13"},{"s":"bus_044400","t":"18:15"},{"s":"bus_043400","t":"18:16"},{"s":"bus_042400","t":"18:17"},{"s":"bus_021400","t":"18:19"},{"s":"bus_040420","t":"18:20"},{"s":"bus_548200","t":"18:21"},{"s":"bus_549200","t":"18:22"},{"s":"bus_550400","t":"18:23"},{"s":"bus_547400","t":"18:24"},{"s":"bus_036400","t":"18:25"},{"s":"bus_035400","t":"18:26"},{"s":"bus_034120","t":"18:28"},{"s":"bus_540400","t":"18:30"},{"s":"bus_541400","t":"18:31"},{"s":"bus_542100","t":"18:32"},{"s":"bus_543400","t":"18:33"},{"s":"bus_566400","t":"18:34"},{"s":"bus_567300","t":"18:36"},{"s":"bus_568300","t":"18:37"},{"s":"bus_569300","t":"18:38"},{"s":"bus_541300","t":"18:40"},{"s":"bus_540300","t":"18:41"},{"s":"bus_034220","t":"18:43"},{"s":"bus_035300","t":"18:44"},{"s":"bus_036300","t":"18:45"},{"s":"bus_547300","t":"18:46"},{"s":"bus_550100","t":"18:48"},{"s":"bus_549100","t":"18:49"},{"s":"bus_548100","t":"18:50"},{"s":"bus_040300","t":"18:52"},{"s":"bus_021300","t":"18:54"},{"s":"bus_042300","t":"18:55"},{"s":"bus_043300","t":"18:56"},{"s":"bus_044320","t":"18:58"},{"s":"bus_018100","t":"18:59"},{"s":"bus_707001","t":"19:02"}]},{"id":"03703_03001_10558","d":"1","st":[{"s":"bus_707220","t":"19:35"},{"s":"bus_018200","t":"19:37"},{"s":"bus_044400","t":"19:39"},{"s":"bus_043400","t":"19:40"},{"s":"bus_042400","t":"19:41"},{"s":"bus_021400","t":"19:42"},{"s":"bus_040420","t":"19:43"},{"s":"bus_548200","t":"19:44"},{"s":"bus_549200","t":"19:45"},{"s":"bus_550400","t":"19:46"},{"s":"bus_547400","t":"19:47"},{"s":"bus_036400","t":"19:48"},{"s":"bus_035400","t":"19:49"},{"s":"bus_034120","t":"19:51"},{"s":"bus_540400","t":"19:53"},{"s":"bus_541400","t":"19:54"},{"s":"bus_542100","t":"19:55"},{"s":"bus_543400","t":"19:56"},{"s":"bus_566400","t":"19:57"},{"s":"bus_567300","t":"19:59"},{"s":"bus_568300","t":"20:00"},{"s":"bus_569300","t":"20:01"},{"s":"bus_541300","t":"20:03"},{"s":"bus_540300","t":"20:04"},{"s":"bus_034220","t":"20:06"},{"s":"bus_035300","t":"20:07"},{"s":"bus_036300","t":"20:08"},{"s":"bus_547300","t":"20:09"},{"s":"bus_550100","t":"20:11"},{"s":"bus_549100","t":"20:12"},{"s":"bus_548100","t":"20:13"},{"s":"bus_040300","t":"20:15"},{"s":"bus_021300","t":"20:17"},{"s":"bus_042300","t":"20:18"},{"s":"bus_043300","t":"20:19"},{"s":"bus_044320","t":"20:20"},{"s":"bus_018100","t":"20:21"},{"s":"bus_707001","t":"20:24"}]},{"id":"03703_03001_10537","d":"1","st":[{"s":"bus_707220","t":"21:06"},{"s":"bus_018200","t":"21:08"},{"s":"bus_044400","t":"21:10"},{"s":"bus_043400","t":"21:11"},{"s":"bus_042400","t":"21:12"},{"s":"bus_021400","t":"21:13"},{"s":"bus_040420","t":"21:14"},{"s":"bus_548200","t":"21:15"},{"s":"bus_549200","t":"21:16"},{"s":"bus_550400","t":"21:17"},{"s":"bus_547400","t":"21:18"},{"s":"bus_036400","t":"21:19"},{"s":"bus_035400","t":"21:20"},{"s":"bus_034120","t":"21:22"},{"s":"bus_540400","t":"21:24"},{"s":"bus_541400","t":"21:25"},{"s":"bus_542100","t":"21:26"},{"s":"bus_543400","t":"21:27"},{"s":"bus_566400","t":"21:28"},{"s":"bus_567300","t":"21:30"},{"s":"bus_568300","t":"21:31"},{"s":"bus_569300","t":"21:32"},{"s":"bus_541300","t":"21:34"},{"s":"bus_540300","t":"21:35"},{"s":"bus_034220","t":"21:37"},{"s":"bus_035300","t":"21:38"},{"s":"bus_036300","t":"21:39"},{"s":"bus_547300","t":"21:40"},{"s":"bus_550100","t":"21:42"},{"s":"bus_549100","t":"21:43"},{"s":"bus_548100","t":"21:44"},{"s":"bus_040300","t":"21:46"},{"s":"bus_021300","t":"21:48"},{"s":"bus_042300","t":"21:49"},{"s":"bus_043300","t":"21:50"},{"s":"bus_044320","t":"21:51"},{"s":"bus_018100","t":"21:52"},{"s":"bus_707001","t":"21:55"}]}],"sundays":[{"id":"03703_02001_15612","d":"1","st":[{"s":"bus_707220","t":"06:17"},{"s":"bus_018200","t":"06:19"},{"s":"bus_044400","t":"06:21"},{"s":"bus_043400","t":"06:22"},{"s":"bus_042400","t":"06:23"},{"s":"bus_021400","t":"06:24"},{"s":"bus_040420","t":"06:25"},{"s":"bus_548200","t":"06:26"},{"s":"bus_549200","t":"06:27"},{"s":"bus_550400","t":"06:28"},{"s":"bus_547400","t":"06:29"},{"s":"bus_036400","t":"06:30"},{"s":"bus_035400","t":"06:31"},{"s":"bus_034120","t":"06:32"},{"s":"bus_540400","t":"06:34"},{"s":"bus_541400","t":"06:35"},{"s":"bus_542100","t":"06:36"},{"s":"bus_543400","t":"06:37"},{"s":"bus_566400","t":"06:38"},{"s":"bus_567300","t":"06:40"},{"s":"bus_568300","t":"06:41"},{"s":"bus_569300","t":"06:42"},{"s":"bus_541300","t":"06:44"},{"s":"bus_540300","t":"06:45"},{"s":"bus_034220","t":"06:47"},{"s":"bus_035300","t":"06:48"},{"s":"bus_036300","t":"06:49"},{"s":"bus_547300","t":"06:50"},{"s":"bus_550100","t":"06:52"},{"s":"bus_549100","t":"06:53"},{"s":"bus_548100","t":"06:54"},{"s":"bus_040300","t":"06:56"},{"s":"bus_021300","t":"06:58"},{"s":"bus_042300","t":"06:59"},{"s":"bus_043300","t":"07:00"},{"s":"bus_044320","t":"07:01"},{"s":"bus_018100","t":"07:02"},{"s":"bus_707001","t":"07:05"}]},{"id":"03703_02001_15645","d":"1","st":[{"s":"bus_707220","t":"07:08"},{"s":"bus_018200","t":"07:10"},{"s":"bus_044400","t":"07:12"},{"s":"bus_043400","t":"07:13"},{"s":"bus_042400","t":"07:14"},{"s":"bus_021400","t":"07:15"},{"s":"bus_040420","t":"07:16"},{"s":"bus_548200","t":"07:17"},{"s":"bus_549200","t":"07:18"},{"s":"bus_550400","t":"07:19"},{"s":"bus_547400","t":"07:20"},{"s":"bus_036400","t":"07:21"},{"s":"bus_035400","t":"07:22"},{"s":"bus_034120","t":"07:23"},{"s":"bus_540400","t":"07:25"},{"s":"bus_541400","t":"07:26"},{"s":"bus_542100","t":"07:27"},{"s":"bus_543400","t":"07:28"},{"s":"bus_566400","t":"07:29"},{"s":"bus_567300","t":"07:31"},{"s":"bus_568300","t":"07:32"},{"s":"bus_569300","t":"07:33"},{"s":"bus_541300","t":"07:35"},{"s":"bus_540300","t":"07:36"},{"s":"bus_034220","t":"07:38"},{"s":"bus_035300","t":"07:39"},{"s":"bus_036300","t":"07:40"},{"s":"bus_547300","t":"07:41"},{"s":"bus_550100","t":"07:43"},{"s":"bus_549100","t":"07:44"},{"s":"bus_548100","t":"07:45"},{"s":"bus_040300","t":"07:47"},{"s":"bus_021300","t":"07:49"},{"s":"bus_042300","t":"07:50"},{"s":"bus_043300","t":"07:51"},{"s":"bus_044320","t":"07:52"},{"s":"bus_018100","t":"07:53"},{"s":"bus_707001","t":"07:56"}]},{"id":"03703_02001_15655","d":"1","st":[{"s":"bus_707220","t":"08:14"},{"s":"bus_018200","t":"08:16"},{"s":"bus_044400","t":"08:18"},{"s":"bus_043400","t":"08:19"},{"s":"bus_042400","t":"08:20"},{"s":"bus_021400","t":"08:21"},{"s":"bus_040420","t":"08:22"},{"s":"bus_548200","t":"08:23"},{"s":"bus_549200","t":"08:24"},{"s":"bus_550400","t":"08:25"},{"s":"bus_547400","t":"08:26"},{"s":"bus_036400","t":"08:27"},{"s":"bus_035400","t":"08:28"},{"s":"bus_034120","t":"08:29"},{"s":"bus_540400","t":"08:31"},{"s":"bus_541400","t":"08:32"},{"s":"bus_542100","t":"08:33"},{"s":"bus_543400","t":"08:34"},{"s":"bus_566400","t":"08:35"},{"s":"bus_567300","t":"08:37"},{"s":"bus_568300","t":"08:38"},{"s":"bus_569300","t":"08:39"},{"s":"bus_541300","t":"08:41"},{"s":"bus_540300","t":"08:42"},{"s":"bus_034220","t":"08:44"},{"s":"bus_035300","t":"08:45"},{"s":"bus_036300","t":"08:46"},{"s":"bus_547300","t":"08:47"},{"s":"bus_550100","t":"08:49"},{"s":"bus_549100","t":"08:50"},{"s":"bus_548100","t":"08:51"},{"s":"bus_040300","t":"08:53"},{"s":"bus_021300","t":"08:55"},{"s":"bus_042300","t":"08:56"},{"s":"bus_043300","t":"08:57"},{"s":"bus_044320","t":"08:59"},{"s":"bus_018100","t":"09:00"},{"s":"bus_707001","t":"09:03"}]},{"id":"03703_02001_15639","d":"1","st":[{"s":"bus_707220","t":"09:11"},{"s":"bus_018200","t":"09:13"},{"s":"bus_044400","t":"09:15"},{"s":"bus_043400","t":"09:16"},{"s":"bus_042400","t":"09:17"},{"s":"bus_021400","t":"09:19"},{"s":"bus_040420","t":"09:20"},{"s":"bus_548200","t":"09:21"},{"s":"bus_549200","t":"09:22"},{"s":"bus_550400","t":"09:23"},{"s":"bus_547400","t":"09:24"},{"s":"bus_036400","t":"09:25"},{"s":"bus_035400","t":"09:26"},{"s":"bus_034120","t":"09:28"},{"s":"bus_540400","t":"09:30"},{"s":"bus_541400","t":"09:31"},{"s":"bus_542100","t":"09:32"},{"s":"bus_543400","t":"09:33"},{"s":"bus_566400","t":"09:34"},{"s":"bus_567300","t":"09:36"},{"s":"bus_568300","t":"09:37"},{"s":"bus_569300","t":"09:38"},{"s":"bus_541300","t":"09:40"},{"s":"bus_540300","t":"09:41"},{"s":"bus_034220","t":"09:43"},{"s":"bus_035300","t":"09:44"},{"s":"bus_036300","t":"09:45"},{"s":"bus_547300","t":"09:46"},{"s":"bus_550100","t":"09:48"},{"s":"bus_549100","t":"09:49"},{"s":"bus_548100","t":"09:50"},{"s":"bus_040300","t":"09:52"},{"s":"bus_021300","t":"09:54"},{"s":"bus_042300","t":"09:55"},{"s":"bus_043300","t":"09:56"},{"s":"bus_044320","t":"09:58"},{"s":"bus_018100","t":"09:59"},{"s":"bus_707001","t":"10:02"}]},{"id":"03703_02001_15619","d":"1","st":[{"s":"bus_707220","t":"10:11"},{"s":"bus_018200","t":"10:13"},{"s":"bus_044400","t":"10:15"},{"s":"bus_043400","t":"10:16"},{"s":"bus_042400","t":"10:17"},{"s":"bus_021400","t":"10:19"},{"s":"bus_040420","t":"10:20"},{"s":"bus_548200","t":"10:21"},{"s":"bus_549200","t":"10:22"},{"s":"bus_550400","t":"10:23"},{"s":"bus_547400","t":"10:24"},{"s":"bus_036400","t":"10:25"},{"s":"bus_035400","t":"10:26"},{"s":"bus_034120","t":"10:28"},{"s":"bus_540400","t":"10:30"},{"s":"bus_541400","t":"10:31"},{"s":"bus_542100","t":"10:32"},{"s":"bus_543400","t":"10:33"},{"s":"bus_566400","t":"10:34"},{"s":"bus_567300","t":"10:36"},{"s":"bus_568300","t":"10:37"},{"s":"bus_569300","t":"10:38"},{"s":"bus_541300","t":"10:40"},{"s":"bus_540300","t":"10:41"},{"s":"bus_034220","t":"10:43"},{"s":"bus_035300","t":"10:44"},{"s":"bus_036300","t":"10:45"},{"s":"bus_547300","t":"10:46"},{"s":"bus_550100","t":"10:48"},{"s":"bus_549100","t":"10:49"},{"s":"bus_548100","t":"10:50"},{"s":"bus_040300","t":"10:52"},{"s":"bus_021300","t":"10:54"},{"s":"bus_042300","t":"10:55"},{"s":"bus_043300","t":"10:56"},{"s":"bus_044320","t":"10:58"},{"s":"bus_018100","t":"10:59"},{"s":"bus_707001","t":"11:02"}]},{"id":"03703_02001_15660","d":"1","st":[{"s":"bus_707220","t":"11:41"},{"s":"bus_018200","t":"11:43"},{"s":"bus_044400","t":"11:45"},{"s":"bus_043400","t":"11:46"},{"s":"bus_042400","t":"11:47"},{"s":"bus_021400","t":"11:49"},{"s":"bus_040420","t":"11:50"},{"s":"bus_548200","t":"11:51"},{"s":"bus_549200","t":"11:52"},{"s":"bus_550400","t":"11:53"},{"s":"bus_547400","t":"11:54"},{"s":"bus_036400","t":"11:55"},{"s":"bus_035400","t":"11:56"},{"s":"bus_034120","t":"11:58"},{"s":"bus_540400","t":"12:00"},{"s":"bus_541400","t":"12:01"},{"s":"bus_542100","t":"12:02"},{"s":"bus_543400","t":"12:03"},{"s":"bus_566400","t":"12:04"},{"s":"bus_567300","t":"12:06"},{"s":"bus_568300","t":"12:07"},{"s":"bus_569300","t":"12:08"},{"s":"bus_541300","t":"12:10"},{"s":"bus_540300","t":"12:11"},{"s":"bus_034220","t":"12:13"},{"s":"bus_035300","t":"12:14"},{"s":"bus_036300","t":"12:15"},{"s":"bus_547300","t":"12:16"},{"s":"bus_550100","t":"12:18"},{"s":"bus_549100","t":"12:19"},{"s":"bus_548100","t":"12:20"},{"s":"bus_040300","t":"12:22"},{"s":"bus_021300","t":"12:24"},{"s":"bus_042300","t":"12:25"},{"s":"bus_043300","t":"12:26"},{"s":"bus_044320","t":"12:28"},{"s":"bus_018100","t":"12:29"},{"s":"bus_707001","t":"12:32"}]},{"id":"03703_02001_15661","d":"1","st":[{"s":"bus_707220","t":"13:11"},{"s":"bus_018200","t":"13:13"},{"s":"bus_044400","t":"13:15"},{"s":"bus_043400","t":"13:16"},{"s":"bus_042400","t":"13:17"},{"s":"bus_021400","t":"13:19"},{"s":"bus_040420","t":"13:20"},{"s":"bus_548200","t":"13:21"},{"s":"bus_549200","t":"13:22"},{"s":"bus_550400","t":"13:23"},{"s":"bus_547400","t":"13:24"},{"s":"bus_036400","t":"13:25"},{"s":"bus_035400","t":"13:26"},{"s":"bus_034120","t":"13:28"},{"s":"bus_540400","t":"13:30"},{"s":"bus_541400","t":"13:31"},{"s":"bus_542100","t":"13:32"},{"s":"bus_543400","t":"13:33"},{"s":"bus_566400","t":"13:34"},{"s":"bus_567300","t":"13:36"},{"s":"bus_568300","t":"13:37"},{"s":"bus_569300","t":"13:38"},{"s":"bus_541300","t":"13:40"},{"s":"bus_540300","t":"13:41"},{"s":"bus_034220","t":"13:43"},{"s":"bus_035300","t":"13:44"},{"s":"bus_036300","t":"13:45"},{"s":"bus_547300","t":"13:46"},{"s":"bus_550100","t":"13:48"},{"s":"bus_549100","t":"13:49"},{"s":"bus_548100","t":"13:50"},{"s":"bus_040300","t":"13:52"},{"s":"bus_021300","t":"13:54"},{"s":"bus_042300","t":"13:55"},{"s":"bus_043300","t":"13:56"},{"s":"bus_044320","t":"13:58"},{"s":"bus_018100","t":"13:59"},{"s":"bus_707001","t":"14:02"}]},{"id":"03703_02001_15622","d":"1","st":[{"s":"bus_707220","t":"14:41"},{"s":"bus_018200","t":"14:43"},{"s":"bus_044400","t":"14:45"},{"s":"bus_043400","t":"14:46"},{"s":"bus_042400","t":"14:47"},{"s":"bus_021400","t":"14:49"},{"s":"bus_040420","t":"14:50"},{"s":"bus_548200","t":"14:51"},{"s":"bus_549200","t":"14:52"},{"s":"bus_550400","t":"14:53"},{"s":"bus_547400","t":"14:54"},{"s":"bus_036400","t":"14:55"},{"s":"bus_035400","t":"14:56"},{"s":"bus_034120","t":"14:58"},{"s":"bus_540400","t":"15:00"},{"s":"bus_541400","t":"15:01"},{"s":"bus_542100","t":"15:02"},{"s":"bus_543400","t":"15:03"},{"s":"bus_566400","t":"15:04"},{"s":"bus_567300","t":"15:06"},{"s":"bus_568300","t":"15:07"},{"s":"bus_569300","t":"15:08"},{"s":"bus_541300","t":"15:10"},{"s":"bus_540300","t":"15:11"},{"s":"bus_034220","t":"15:13"},{"s":"bus_035300","t":"15:14"},{"s":"bus_036300","t":"15:15"},{"s":"bus_547300","t":"15:16"},{"s":"bus_550100","t":"15:18"},{"s":"bus_549100","t":"15:19"},{"s":"bus_548100","t":"15:20"},{"s":"bus_040300","t":"15:22"},{"s":"bus_021300","t":"15:24"},{"s":"bus_042300","t":"15:25"},{"s":"bus_043300","t":"15:26"},{"s":"bus_044320","t":"15:28"},{"s":"bus_018100","t":"15:29"},{"s":"bus_707001","t":"15:32"}]},{"id":"03703_02001_15730","d":"1","st":[{"s":"bus_707220","t":"16:11"},{"s":"bus_018200","t":"16:13"},{"s":"bus_044400","t":"16:15"},{"s":"bus_043400","t":"16:16"},{"s":"bus_042400","t":"16:17"},{"s":"bus_021400","t":"16:19"},{"s":"bus_040420","t":"16:20"},{"s":"bus_548200","t":"16:21"},{"s":"bus_549200","t":"16:22"},{"s":"bus_550400","t":"16:23"},{"s":"bus_547400","t":"16:24"},{"s":"bus_036400","t":"16:25"},{"s":"bus_035400","t":"16:26"},{"s":"bus_034120","t":"16:28"},{"s":"bus_540400","t":"16:30"},{"s":"bus_541400","t":"16:31"},{"s":"bus_542100","t":"16:32"},{"s":"bus_543400","t":"16:33"},{"s":"bus_566400","t":"16:34"},{"s":"bus_567300","t":"16:36"},{"s":"bus_568300","t":"16:37"},{"s":"bus_569300","t":"16:38"},{"s":"bus_541300","t":"16:40"},{"s":"bus_540300","t":"16:41"},{"s":"bus_034220","t":"16:43"},{"s":"bus_035300","t":"16:44"},{"s":"bus_036300","t":"16:45"},{"s":"bus_547300","t":"16:46"},{"s":"bus_550100","t":"16:48"},{"s":"bus_549100","t":"16:49"},{"s":"bus_548100","t":"16:50"},{"s":"bus_040300","t":"16:52"},{"s":"bus_021300","t":"16:54"},{"s":"bus_042300","t":"16:55"},{"s":"bus_043300","t":"16:56"},{"s":"bus_044320","t":"16:58"},{"s":"bus_018100","t":"16:59"},{"s":"bus_707001","t":"17:02"}]},{"id":"03703_02001_15654","d":"1","st":[{"s":"bus_707220","t":"17:11"},{"s":"bus_018200","t":"17:13"},{"s":"bus_044400","t":"17:15"},{"s":"bus_043400","t":"17:16"},{"s":"bus_042400","t":"17:17"},{"s":"bus_021400","t":"17:19"},{"s":"bus_040420","t":"17:20"},{"s":"bus_548200","t":"17:21"},{"s":"bus_549200","t":"17:22"},{"s":"bus_550400","t":"17:23"},{"s":"bus_547400","t":"17:24"},{"s":"bus_036400","t":"17:25"},{"s":"bus_035400","t":"17:26"},{"s":"bus_034120","t":"17:28"},{"s":"bus_540400","t":"17:30"},{"s":"bus_541400","t":"17:31"},{"s":"bus_542100","t":"17:32"},{"s":"bus_543400","t":"17:33"},{"s":"bus_566400","t":"17:34"},{"s":"bus_567300","t":"17:36"},{"s":"bus_568300","t":"17:37"},{"s":"bus_569300","t":"17:38"},{"s":"bus_541300","t":"17:40"},{"s":"bus_540300","t":"17:41"},{"s":"bus_034220","t":"17:43"},{"s":"bus_035300","t":"17:44"},{"s":"bus_036300","t":"17:45"},{"s":"bus_547300","t":"17:46"},{"s":"bus_550100","t":"17:48"},{"s":"bus_549100","t":"17:49"},{"s":"bus_548100","t":"17:50"},{"s":"bus_040300","t":"17:52"},{"s":"bus_021300","t":"17:54"},{"s":"bus_042300","t":"17:55"},{"s":"bus_043300","t":"17:56"},{"s":"bus_044320","t":"17:58"},{"s":"bus_018100","t":"17:59"},{"s":"bus_707001","t":"18:02"}]},{"id":"03703_02001_15731","d":"1","st":[{"s":"bus_707220","t":"18:11"},{"s":"bus_018200","t":"18:13"},{"s":"bus_044400","t":"18:15"},{"s":"bus_043400","t":"18:16"},{"s":"bus_042400","t":"18:17"},{"s":"bus_021400","t":"18:19"},{"s":"bus_040420","t":"18:20"},{"s":"bus_548200","t":"18:21"},{"s":"bus_549200","t":"18:22"},{"s":"bus_550400","t":"18:23"},{"s":"bus_547400","t":"18:24"},{"s":"bus_036400","t":"18:25"},{"s":"bus_035400","t":"18:26"},{"s":"bus_034120","t":"18:28"},{"s":"bus_540400","t":"18:30"},{"s":"bus_541400","t":"18:31"},{"s":"bus_542100","t":"18:32"},{"s":"bus_543400","t":"18:33"},{"s":"bus_566400","t":"18:34"},{"s":"bus_567300","t":"18:36"},{"s":"bus_568300","t":"18:37"},{"s":"bus_569300","t":"18:38"},{"s":"bus_541300","t":"18:40"},{"s":"bus_540300","t":"18:41"},{"s":"bus_034220","t":"18:43"},{"s":"bus_035300","t":"18:44"},{"s":"bus_036300","t":"18:45"},{"s":"bus_547300","t":"18:46"},{"s":"bus_550100","t":"18:48"},{"s":"bus_549100","t":"18:49"},{"s":"bus_548100","t":"18:50"},{"s":"bus_040300","t":"18:52"},{"s":"bus_021300","t":"18:54"},{"s":"bus_042300","t":"18:55"},{"s":"bus_043300","t":"18:56"},{"s":"bus_044320","t":"18:58"},{"s":"bus_018100","t":"18:59"},{"s":"bus_707001","t":"19:02"}]},{"id":"03703_02001_15732","d":"1","st":[{"s":"bus_707220","t":"19:35"},{"s":"bus_018200","t":"19:37"},{"s":"bus_044400","t":"19:39"},{"s":"bus_043400","t":"19:40"},{"s":"bus_042400","t":"19:41"},{"s":"bus_021400","t":"19:42"},{"s":"bus_040420","t":"19:43"},{"s":"bus_548200","t":"19:44"},{"s":"bus_549200","t":"19:45"},{"s":"bus_550400","t":"19:46"},{"s":"bus_547400","t":"19:47"},{"s":"bus_036400","t":"19:48"},{"s":"bus_035400","t":"19:49"},{"s":"bus_034120","t":"19:51"},{"s":"bus_540400","t":"19:53"},{"s":"bus_541400","t":"19:54"},{"s":"bus_542100","t":"19:55"},{"s":"bus_543400","t":"19:56"},{"s":"bus_566400","t":"19:57"},{"s":"bus_567300","t":"19:59"},{"s":"bus_568300","t":"20:00"},{"s":"bus_569300","t":"20:01"},{"s":"bus_541300","t":"20:03"},{"s":"bus_540300","t":"20:04"},{"s":"bus_034220","t":"20:06"},{"s":"bus_035300","t":"20:07"},{"s":"bus_036300","t":"20:08"},{"s":"bus_547300","t":"20:09"},{"s":"bus_550100","t":"20:11"},{"s":"bus_549100","t":"20:12"},{"s":"bus_548100","t":"20:13"},{"s":"bus_040300","t":"20:15"},{"s":"bus_021300","t":"20:17"},{"s":"bus_042300","t":"20:18"},{"s":"bus_043300","t":"20:19"},{"s":"bus_044320","t":"20:20"},{"s":"bus_018100","t":"20:21"},{"s":"bus_707001","t":"20:24"}]},{"id":"03703_02001_15711","d":"1","st":[{"s":"bus_707220","t":"21:06"},{"s":"bus_018200","t":"21:08"},{"s":"bus_044400","t":"21:10"},{"s":"bus_043400","t":"21:11"},{"s":"bus_042400","t":"21:12"},{"s":"bus_021400","t":"21:13"},{"s":"bus_040420","t":"21:14"},{"s":"bus_548200","t":"21:15"},{"s":"bus_549200","t":"21:16"},{"s":"bus_550400","t":"21:17"},{"s":"bus_547400","t":"21:18"},{"s":"bus_036400","t":"21:19"},{"s":"bus_035400","t":"21:20"},{"s":"bus_034120","t":"21:22"},{"s":"bus_540400","t":"21:24"},{"s":"bus_541400","t":"21:25"},{"s":"bus_542100","t":"21:26"},{"s":"bus_543400","t":"21:27"},{"s":"bus_566400","t":"21:28"},{"s":"bus_567300","t":"21:30"},{"s":"bus_568300","t":"21:31"},{"s":"bus_569300","t":"21:32"},{"s":"bus_541300","t":"21:34"},{"s":"bus_540300","t":"21:35"},{"s":"bus_034220","t":"21:37"},{"s":"bus_035300","t":"21:38"},{"s":"bus_036300","t":"21:39"},{"s":"bus_547300","t":"21:40"},{"s":"bus_550100","t":"21:42"},{"s":"bus_549100","t":"21:43"},{"s":"bus_548100","t":"21:44"},{"s":"bus_040300","t":"21:46"},{"s":"bus_021300","t":"21:48"},{"s":"bus_042300","t":"21:49"},{"s":"bus_043300","t":"21:50"},{"s":"bus_044320","t":"21:51"},{"s":"bus_018100","t":"21:52"},{"s":"bus_707001","t":"21:55"}]}]}